ft_store/__init__.py
ft_store/sensor.py
server/AESCipher.py
server/RSACipher.py
server/__init__.py
server/config.py
server/decrypt.py
server/generate_key.py
server/get_data.py
server/main.py
ekyc_sensor_fts-0.1.dist-info/METADATA
ekyc_sensor_fts-0.1.dist-info/WHEEL
ekyc_sensor_fts-0.1.dist-info/top_level.txt
ekyc_sensor_fts-0.1.dist-info/RECORD
