Metadata-Version: 2.1
Name: ekyc_sensor_fts
Version: 0.1
Summary: Decrypt and extract data
Home-page: https://github.com/data-science-general-1/ekyc_sensor_fake_detector_featurestore
Author: Hoan Dao
Author-email: hoandq@vnpt.vn
Classifier: Programming Language :: Python :: 3
Classifier: License :: OSI Approved :: MIT License
Classifier: Operating System :: OS Independent
Requires-Python: >=3.6
